hello_from_ned/__init__.py
hello_from_ned/hello_from_ned.py
hello_from_ned-0.0.2.dist-info/METADATA
hello_from_ned-0.0.2.dist-info/WHEEL
hello_from_ned-0.0.2.dist-info/top_level.txt
hello_from_ned-0.0.2.dist-info/RECORD
